{
  "manifest_version": 3,
  "name": "__MSG_extName__",
  "description": "__MSG_extDescription__",
  "version": "1.6.1",
  "default_locale": "en",
  "browser_specific_settings": {
    "gecko": {
      "id": "let-it-snow@example.com",
      "strict_min_version": "109.0"
    }
  },
  "icons": {
    "16": "src/icons/icon-16.png",
    "48": "src/icons/icon-48.png",
    "128": "src/icons/icon-128.png"
  },
  "action": {
    "default_popup": "src/popup/popup.html",
    "default_title": "__MSG_extName__"
  },
  "permissions": [
    "activeTab",
    "storage",
    "scripting"
  ],
  "host_permissions": [
    "<all_urls>"
  ],
  "content_scripts": [
    {
      "matches": [
        "<all_urls>"
      ],
      "js": [
        "src/content/index.js"
      ],
      "run_at": "document_end"
    }
  ]
}
